pydupes.py
pydupes-0.6.1.dist-info/entry_points.txt
pydupes-0.6.1.dist-info/LICENSE
pydupes-0.6.1.dist-info/WHEEL
pydupes-0.6.1.dist-info/METADATA
pydupes-0.6.1.dist-info/RECORD
